{
    "markers":[
        {
            "name":"Parkas1",
            "coords":[
                    54.687157,25.279652
            ],
            "info":"lorem ipsum",
            "pictures":[
                "/images/picture1.png","/images/picture2.png","/images/picture3.png"
            ],
            "category":"park",
            "thumbnail":"/images/tpicture.jpg",
            "rating":5
        },
        {
            "name":"Parkas2",
            "coords":[
                25.8986,14.5687
            ],
            "info":"lorem ipsum2",
            "pictures":[
                "/images/picture1.png","/images/picture2.png","/images/picture3.png"
            ],
            "category":"monument",
            "thumbnail":"/images/tpicture.jpg",
            "rating":5
        }
    ]
}